{
    "wp": [
        {
            "dist_cm": 75,
            "dist_px": 25,
            "angle_deg": 0,
            "turn_signed_deg": 0
        },
        {
            "dist_cm": 75,
            "dist_px": 25,
            "angle_deg": 90,
            "turn_signed_deg": 90
        },
        {
            "dist_cm": 78,
            "dist_px": 26,
            "angle_deg": 86,
            "turn_signed_deg": 86
        },
        {
            "dist_cm": 69,
            "dist_px": 23,
            "angle_deg": 92,
            "turn_signed_deg": 92
        }
    ],
    "pos": [
        [
            380,
            360
        ],
        [
            381,
            335
        ],
        [
            356,
            334
        ],
        [
            357,
            360
        ],
        [
            380,
            360
        ]
    ],
    "meta": {
        "mode": "FREE",
        "speed_cm_s": 30,
        "height_cm": 90,
        "cm_per_px": 3.0,
        "center_px": [
            380,
            360
        ]
    }
}